PYLINQ/__init__.py
LINQ_cython-0.2.4.dist-info/METADATA
LINQ_cython-0.2.4.dist-info/WHEEL
LINQ_cython-0.2.4.dist-info/top_level.txt
LINQ_cython-0.2.4.dist-info/RECORD
