Metadata-Version: 2.1
Name: LINQ-cython
Version: 0.2.4
Summary: ('和c#一样使用方式的linq', 'the linq like c#,and will speed up  by cython')
Home-page: https://github.com/beincy/PYLINQ
Author: 卞辉（beincy）
Author-email: bianhui0524@sina.com
Maintainer: 卞辉(beincy)
Maintainer-email: bianhui0524@sina.com
License: MIT
Platform: all
Classifier: Development Status :: 4 - Beta
Classifier: License :: OSI Approved :: MIT License
Classifier: Programming Language :: Python :: 3.2
Classifier: Programming Language :: Python :: 3.3
Classifier: Programming Language :: Python :: 3.4
Classifier: Programming Language :: Python :: 3.5
Classifier: Programming Language :: Python :: 3.6
Classifier: Programming Language :: Python :: 3.7
